<?xml version='1.0' encoding='utf-8'?>
<!-- FreeCAD DocumentObject -->
<Document SchemaVersion="4" FileVersion="2">
<Object name="Sketch" Extensions="True">
  <Extensions Count="1">
    <Extension type="Part::AttachExtension" name="AttachExtension">
    </Extension>
  </Extensions>
  <Properties Count="21" TransientCount="1">
    <_Property name="_ElementMapVersion" type="App::PropertyString" status="234881024"/>
    <Property name="AttacherType" type="App::PropertyString" status="8">
      <String value="Attacher::AttachEnginePlane"/>
    </Property>
    <Property name="AttachmentOffset" type="App::PropertyPlacement" status="8">
      <PropertyPlacement Px="0" Py="0" Pz="0" Q0="0" Q1="0" Q2="0" Q3="1" A="0" Ox="0" Oy="0" Oz="1"/>
    </Property>
    <Property name="ColoredElements" type="App::PropertyLinkSubHidden" status="218103808">
      <LinkSub value="" count="0">
      </LinkSub>
    </Property>
    <Property name="Constraints" type="Sketcher::PropertyConstraintList">
      <ConstraintList count="25">
        <Constrain Name="" Type="3" Value="0" First="0" FirstPos="0" Second="-2000" SecondPos="0" Third="-2000" ThirdPos="0" LabelDistance="10" LabelPosition="0" IsDriving="1" IsInVirtualSpace="0" IsActive="1" />
        <Constrain Name="" Type="1" Value="0" First="0" FirstPos="2" Second="1" SecondPos="1" Third="-2000" ThirdPos="0" LabelDistance="10" LabelPosition="0" IsDriving="1" IsInVirtualSpace="0" IsActive="1" />
        <Constrain Name="" Type="3" Value="0" First="2" FirstPos="0" Second="-2000" SecondPos="0" Third="-2000" ThirdPos="0" LabelDistance="10" LabelPosition="0" IsDriving="1" IsInVirtualSpace="0" IsActive="1" />
        <Constrain Name="" Type="1" Value="0" First="2" FirstPos="2" Second="3" SecondPos="1" Third="-2000" ThirdPos="0" LabelDistance="10" LabelPosition="0" IsDriving="1" IsInVirtualSpace="0" IsActive="1" />
        <Constrain Name="" Type="2" Value="0" First="3" FirstPos="0" Second="-2000" SecondPos="0" Third="-2000" ThirdPos="0" LabelDistance="10" LabelPosition="0" IsDriving="1" IsInVirtualSpace="0" IsActive="1" />
        <Constrain Name="" Type="1" Value="0" First="3" FirstPos="2" Second="4" SecondPos="1" Third="-2000" ThirdPos="0" LabelDistance="10" LabelPosition="0" IsDriving="1" IsInVirtualSpace="0" IsActive="1" />
        <Constrain Name="" Type="2" Value="0" First="1" FirstPos="0" Second="-2000" SecondPos="0" Third="-2000" ThirdPos="0" LabelDistance="10" LabelPosition="0" IsDriving="1" IsInVirtualSpace="0" IsActive="1" />
        <Constrain Name="" Type="13" Value="0" First="3" FirstPos="2" Second="-2" SecondPos="0" Third="-2000" ThirdPos="0" LabelDistance="10" LabelPosition="0" IsDriving="1" IsInVirtualSpace="0" IsActive="1" />
        <Constrain Name="" Type="1" Value="0" First="4" FirstPos="2" Second="-1" SecondPos="1" Third="-2000" ThirdPos="0" LabelDistance="10" LabelPosition="0" IsDriving="1" IsInVirtualSpace="0" IsActive="1" />
        <Constrain Name="" Type="1" Value="0" First="4" FirstPos="2" Second="5" SecondPos="1" Third="-2000" ThirdPos="0" LabelDistance="10" LabelPosition="0" IsDriving="1" IsInVirtualSpace="0" IsActive="1" />
        <Constrain Name="" Type="14" Value="0" First="2" FirstPos="1" Second="7" SecondPos="1" Third="-2" ThirdPos="0" LabelDistance="10" LabelPosition="0" IsDriving="1" IsInVirtualSpace="0" IsActive="1" />
        <Constrain Name="Dia_Shaft_slimmed" Type="7" Value="2.21" First="7" FirstPos="1" Second="2" SecondPos="1" Third="-2000" ThirdPos="0" LabelDistance="2.151144742965698" LabelPosition="4.271422386169434" IsDriving="1" IsInVirtualSpace="0" IsActive="1" />
        <Constrain Name="Height_Collar" Type="8" Value="0.64" First="0" FirstPos="2" Second="2" SecondPos="1" Third="-2000" ThirdPos="0" LabelDistance="3.317566394805908" LabelPosition="1.54963219165802" IsDriving="1" IsInVirtualSpace="0" IsActive="1" />
        <Constrain Name="Height" Type="8" Value="13.2" First="4" FirstPos="2" Second="4" SecondPos="1" Third="-2000" ThirdPos="0" LabelDistance="3.609287023544312" LabelPosition="0" IsDriving="1" IsInVirtualSpace="0" IsActive="1" />
        <Constrain Name="" Type="1" Value="0" First="2" FirstPos="1" Second="8" SecondPos="1" Third="-2000" ThirdPos="0" LabelDistance="10" LabelPosition="0" IsDriving="1" IsInVirtualSpace="0" IsActive="1" />
        <Constrain Name="" Type="2" Value="0" First="8" FirstPos="0" Second="-2000" SecondPos="0" Third="-2000" ThirdPos="0" LabelDistance="10" LabelPosition="0" IsDriving="1" IsInVirtualSpace="0" IsActive="1" />
        <Constrain Name="" Type="1" Value="0" First="8" FirstPos="2" Second="9" SecondPos="1" Third="-2000" ThirdPos="0" LabelDistance="10" LabelPosition="0" IsDriving="1" IsInVirtualSpace="0" IsActive="1" />
        <Constrain Name="" Type="1" Value="0" First="9" FirstPos="2" Second="1" SecondPos="2" Third="-2000" ThirdPos="0" LabelDistance="10" LabelPosition="0" IsDriving="1" IsInVirtualSpace="0" IsActive="1" />
        <Constrain Name="" Type="3" Value="0" First="9" FirstPos="0" Second="-2000" SecondPos="0" Third="-2000" ThirdPos="0" LabelDistance="10" LabelPosition="0" IsDriving="1" IsInVirtualSpace="0" IsActive="1" />
        <Constrain Name="" Type="14" Value="0" First="10" FirstPos="1" Second="1" SecondPos="2" Third="-2" ThirdPos="0" LabelDistance="10" LabelPosition="0" IsDriving="1" IsInVirtualSpace="0" IsActive="1" />
        <Constrain Name="Da_Collar" Type="7" Value="3.05" First="10" FirstPos="1" Second="1" SecondPos="2" Third="-2000" ThirdPos="0" LabelDistance="0.3170017898082733" LabelPosition="4.539703845977783" IsDriving="1" IsInVirtualSpace="0" IsActive="1" />
        <Constrain Name="" Type="2" Value="0" First="5" FirstPos="0" Second="-2000" SecondPos="0" Third="-2000" ThirdPos="0" LabelDistance="10" LabelPosition="0" IsDriving="1" IsInVirtualSpace="0" IsActive="1" />
        <Constrain Name="" Type="14" Value="0" First="6" FirstPos="1" Second="0" SecondPos="1" Third="-2" ThirdPos="0" LabelDistance="10" LabelPosition="0" IsDriving="1" IsInVirtualSpace="0" IsActive="1" />
        <Constrain Name="Dia_Shaft" Type="7" Value="2.39" First="6" FirstPos="1" Second="0" SecondPos="1" Third="-2000" ThirdPos="0" LabelDistance="0.6750795245170593" LabelPosition="3.255100965499878" IsDriving="1" IsInVirtualSpace="0" IsActive="1" />
        <Constrain Name="" Type="1" Value="0" First="0" FirstPos="1" Second="5" SecondPos="2" Third="-2000" ThirdPos="0" LabelDistance="10" LabelPosition="0" IsDriving="1" IsInVirtualSpace="0" IsActive="1" />
      </ConstraintList>
    </Property>
    <Property name="Dia_Shaft" type="App::PropertyLength" group="Base" attr="0" ro="0" hide="0" doc="" status="2097152">
      <Float value="2.39"/>
    </Property>
    <Property name="Exports" type="App::PropertyLinkListHidden" status="67108864">
      <LinkList count="0">
      </LinkList>
    </Property>
    <Property name="ExpressionEngine" type="App::PropertyExpressionEngine" status="67108864">
      <ExpressionEngine count="2" cdata="1">
        <Expressions><![CDATA[
0:.Constraints.Dia_Shaft
0:Dia_Shaft
0:

0:.Constraints.Height
0:Height
0:

]]>
        </Expressions>
      </ExpressionEngine>
    </Property>
    <Property name="ExternalGeo" type="Part::PropertyGeometryList" status="67108864">
      <GeometryList count="2">
        <Geometry type="Part::GeomLineSegment" id="-1" migrated="1">
          <GeoExtensions count="2">
            <GeoExtension type="Sketcher::SketchGeometryExtension" id="-1" internalGeometryType="0" geometryModeFlags="00000000000000000000000000000010"/>
            <GeoExtension type="Sketcher::ExternalGeometryExtension" Ref="" Flags="0"/>
          </GeoExtensions>
          <LineSegment StartX="0" StartY="0" StartZ="0" EndX="1" EndY="0" EndZ="0"/>
          <Construction value="1"/>
        </Geometry>
        <Geometry type="Part::GeomLineSegment" id="-2" migrated="1">
          <GeoExtensions count="2">
            <GeoExtension type="Sketcher::SketchGeometryExtension" id="-2" internalGeometryType="0" geometryModeFlags="00000000000000000000000000000010"/>
            <GeoExtension type="Sketcher::ExternalGeometryExtension" Ref="" Flags="0"/>
          </GeoExtensions>
          <LineSegment StartX="0" StartY="0" StartZ="0" EndX="0" EndY="1" EndZ="0"/>
          <Construction value="1"/>
        </Geometry>
      </GeometryList>
    </Property>
    <Property name="ExternalGeometry" type="App::PropertyLinkSubList" status="16777216">
      <LinkSubList count="0">
      </LinkSubList>
    </Property>
    <Property name="FullyConstrained" type="App::PropertyBool" status="218103808">
      <Bool value="false"/>
    </Property>
    <Property name="Geometry" type="Part::PropertyGeometryList" status="8192">
      <GeometryList count="11">
        <Geometry type="Part::GeomLineSegment" id="195" migrated="1">
          <GeoExtensions count="1">
            <GeoExtension type="Sketcher::SketchGeometryExtension" id="195" internalGeometryType="0" geometryModeFlags="00000000000000000000000000000000"/>
          </GeoExtensions>
          <LineSegment StartX="1.195" StartY="0" StartZ="0" EndX="1.195" EndY="6.533545" EndZ="0"/>
          <Construction value="0"/>
        </Geometry>
        <Geometry type="Part::GeomLineSegment" id="196" migrated="1">
          <GeoExtensions count="1">
            <GeoExtension type="Sketcher::SketchGeometryExtension" id="196" internalGeometryType="0" geometryModeFlags="00000000000000000000000000000000"/>
          </GeoExtensions>
          <LineSegment StartX="1.195" StartY="6.533545" StartZ="0" EndX="1.525" EndY="6.533545" EndZ="0"/>
          <Construction value="0"/>
        </Geometry>
        <Geometry type="Part::GeomLineSegment" id="197" migrated="1">
          <GeoExtensions count="1">
            <GeoExtension type="Sketcher::SketchGeometryExtension" id="197" internalGeometryType="0" geometryModeFlags="00000000000000000000000000000000"/>
          </GeoExtensions>
          <LineSegment StartX="1.105" StartY="7.173545" StartZ="0" EndX="1.105" EndY="13.2" EndZ="0"/>
          <Construction value="0"/>
        </Geometry>
        <Geometry type="Part::GeomLineSegment" id="198" migrated="1">
          <GeoExtensions count="1">
            <GeoExtension type="Sketcher::SketchGeometryExtension" id="198" internalGeometryType="0" geometryModeFlags="00000000000000000000000000000000"/>
          </GeoExtensions>
          <LineSegment StartX="1.105" StartY="13.2" StartZ="0" EndX="0" EndY="13.2" EndZ="0"/>
          <Construction value="0"/>
        </Geometry>
        <Geometry type="Part::GeomLineSegment" id="199" migrated="1">
          <GeoExtensions count="1">
            <GeoExtension type="Sketcher::SketchGeometryExtension" id="199" internalGeometryType="0" geometryModeFlags="00000000000000000000000000000000"/>
          </GeoExtensions>
          <LineSegment StartX="0" StartY="13.2" StartZ="0" EndX="0" EndY="0" EndZ="0"/>
          <Construction value="0"/>
        </Geometry>
        <Geometry type="Part::GeomLineSegment" id="200" migrated="1">
          <GeoExtensions count="1">
            <GeoExtension type="Sketcher::SketchGeometryExtension" id="200" internalGeometryType="0" geometryModeFlags="00000000000000000000000000000000"/>
          </GeoExtensions>
          <LineSegment StartX="0" StartY="0" StartZ="0" EndX="1.195" EndY="0" EndZ="0"/>
          <Construction value="0"/>
        </Geometry>
        <Geometry type="Part::GeomPoint" id="201" migrated="1">
          <GeoExtensions count="1">
            <GeoExtension type="Sketcher::SketchGeometryExtension" id="201" internalGeometryType="0" geometryModeFlags="00000000000000000000000000000010"/>
          </GeoExtensions>
          <GeomPoint X="-1.195" Y="0" Z="0"/>
          <Construction value="1"/>
        </Geometry>
        <Geometry type="Part::GeomPoint" id="202" migrated="1">
          <GeoExtensions count="1">
            <GeoExtension type="Sketcher::SketchGeometryExtension" id="202" internalGeometryType="0" geometryModeFlags="00000000000000000000000000000010"/>
          </GeoExtensions>
          <GeomPoint X="-1.105" Y="7.173545" Z="0"/>
          <Construction value="1"/>
        </Geometry>
        <Geometry type="Part::GeomLineSegment" id="203" migrated="1">
          <GeoExtensions count="1">
            <GeoExtension type="Sketcher::SketchGeometryExtension" id="203" internalGeometryType="0" geometryModeFlags="00000000000000000000000000000000"/>
          </GeoExtensions>
          <LineSegment StartX="1.105" StartY="7.173545" StartZ="0" EndX="1.525" EndY="7.173545" EndZ="0"/>
          <Construction value="0"/>
        </Geometry>
        <Geometry type="Part::GeomLineSegment" id="204" migrated="1">
          <GeoExtensions count="1">
            <GeoExtension type="Sketcher::SketchGeometryExtension" id="204" internalGeometryType="0" geometryModeFlags="00000000000000000000000000000000"/>
          </GeoExtensions>
          <LineSegment StartX="1.525" StartY="7.173545" StartZ="0" EndX="1.525" EndY="6.533545" EndZ="0"/>
          <Construction value="0"/>
        </Geometry>
        <Geometry type="Part::GeomPoint" id="205" migrated="1">
          <GeoExtensions count="1">
            <GeoExtension type="Sketcher::SketchGeometryExtension" id="205" internalGeometryType="0" geometryModeFlags="00000000000000000000000000000010"/>
          </GeoExtensions>
          <GeomPoint X="-1.525" Y="6.533545" Z="0"/>
          <Construction value="1"/>
        </Geometry>
      </GeometryList>
    </Property>
    <Property name="Height" type="App::PropertyLength" group="Base" attr="0" ro="0" hide="0" doc="" status="2097152">
      <Float value="13.2"/>
    </Property>
    <Property name="Label" type="App::PropertyString" status="134217728">
      <String value="Pin Sketch"/>
    </Property>
    <Property name="Label2" type="App::PropertyString" status="128">
      <String value=""/>
    </Property>
    <Property name="MapMode" type="App::PropertyEnumeration">
      <Integer value="0"/>
    </Property>
    <Property name="MapPathParameter" type="App::PropertyFloat" status="8">
      <Float value="0"/>
    </Property>
    <Property name="MapReversed" type="App::PropertyBool" status="8">
      <Bool value="false"/>
    </Property>
    <Property name="Placement" type="App::PropertyPlacement" status="8388608">
      <PropertyPlacement Px="0" Py="0" Pz="0" Q0="0.7071067811865477" Q1="-0" Q2="-0" Q3="0.7071067811865474" A="1.570796326794897" Ox="1" Oy="-0" Oz="-0"/>
    </Property>
    <Property name="Shape" type="Part::PropertyPartShape">
      <Part ElementMap="0.15.70200.3" brep="1">
<![CDATA[

CASCADE Topology V1, (c) Matra-Datavision
Locations 4
1
              1               0              -0               0 
             -0               0              -1               0 
              0               1               0               0 
1
              1               0               0               0 
              0               0              -1               0 
              0               1               0               0 
1
              1               0               0               0 
              0               1               0               0 
              0               0               1               0 
2  2 -1 3 -1 0
Curve2ds 6
1 6.2831853071795862 0 0 1 
1 0 0 0 1 
1 6.2831853071795862 0 0 1 
1 0 0 0 1 
1 6.2831853071795862 0 0 1 
1 0 0 0 1 
Curves 8
1 1.105 7.1735449999999998 0 0 1 0 
1 1.105 13.199999999999999 0 -1 0 0 
1 0 13.199999999999999 0 0 -1 0 
1 0 0 0 1 0 0 
1 1.1950000000000001 0 0 0 1 0 
1 1.1950000000000001 6.5335450000000002 0 1 0 0 
1 1.5249999999999999 7.1735449999999998 0 0 -1 0 
1 1.105 7.1735449999999998 0 1 0 0 
Polygon3D 0
PolygonOnTriangulations 0
Surfaces 3
2 0 0 7.1735449999999998 0 0 1 1 1.4399999999999999e-15 -0 -1.4399999999999999e-15 1 0 1.105
2 0 0 0 0 0 1 1 0 -0 -0 1 0 1.1950000000000001
2 0 0 7.1735449999999998 -0 -0 -1 1 1.0399999999999999e-15 -0 -1.0399999999999999e-15 1 -0 1.5249999999999999
Triangulations 0

TShapes 17
Ve
1e-07
1.105 7.173545 0
0 0

0101101
*
Ve
1e-07
1.105 13.2 0
0 0

0101101
*
Ed
 1e-07 1 1 0
1  1 0 0 6.026455
3  1 2CN 1 4 0 6.026455
0

0101000
+17 0 -16 0 *
Ve
1e-07
0 13.2 0
0 0

0101101
*
Ed
 1e-07 1 1 0
1  2 0 0 1.105
0

0101000
+16 0 -14 0 *
Ve
1e-07
0 0 0
0 0

0101101
*
Ed
 1e-07 1 1 0
1  3 0 0 13.2
0

0101000
+14 0 -12 0 *
Ve
1e-07
1.195 0 0
0 0

0101101
*
Ed
 1e-07 1 1 0
1  4 0 0 1.195
0

0101000
+12 0 -10 0 *
Ve
1e-07
1.195 6.533545 0
0 0

0101101
*
Ed
 1e-07 1 1 0
1  5 0 0 6.533545
3  3 4CN 2 4 0 6.533545
0

0101000
+10 0 -8 0 *
Ve
1e-07
1.525 6.533545 0
0 0

0101101
*
Ed
 1e-07 1 1 0
1  6 0 0 0.33
0

0101000
+8 0 -6 0 *
Ve
1e-07
1.525 7.173545 0
0 0

0101101
*
Ed
 1e-07 1 1 0
1  7 0 0 0.64
3  5 6CN 3 4 0 0.64
0

0101000
+4 0 -6 0 *
Ed
 1e-07 1 1 0
1  8 0 0 0.42
0

0101000
+17 0 -4 0 *
Wi

0101100
+15 0 +13 0 +11 0 +9 0 +7 0 +5 0 -3 0 -2 0 *

+1 1 ]]>
      </Part>
      <ElementMap count="1">
<![CDATA[
Dummy	Dummy 0
]]>
      </ElementMap>
    </Property>
    <Property name="Support" type="App::PropertyLinkSubList">
      <LinkSubList count="0">
      </LinkSubList>
    </Property>
    <Property name="Visibility" type="App::PropertyBool" status="648">
      <Bool value="false"/>
    </Property>
  </Properties>
</Object>
</Document>
